banditcoot/__init__.py
banditcoot/algorithms/__init__.py
banditcoot/algorithms/_epsilon_greedy.py
banditcoot/algorithms/_softmax.py
banditcoot/arms/__init__.py
banditcoot/arms/_bernoulli.py
banditcoot/utility/__init__.py
banditcoot/utility/_batch_monte_carlo_sim.py
banditcoot/utility/_monte_carlo_sim.py
banditcoot-0.2.0.dist-info/WHEEL
banditcoot-0.2.0.dist-info/METADATA
banditcoot-0.2.0.dist-info/RECORD
