Metadata-Version: 2.1
Name: banditcoot
Version: 0.2.0
Summary: Python module for developing and testing multi-armed bandits
License: MIT
Author: dan-kwon
Author-email: danielkwon02@gmail.com
Requires-Python: >=3.9,<4.0
Classifier: License :: OSI Approved :: MIT License
Classifier: Programming Language :: Python :: 3
Classifier: Programming Language :: Python :: 3.9
Classifier: Programming Language :: Python :: 3.10
Classifier: Programming Language :: Python :: 3.11
Requires-Dist: pandas (>=1.5.3,<2.0.0)
Requires-Dist: pytest (>=7.4.0,<8.0.0)
